bayesian_sgm/__init__.py
bayesian_sgm/normalize.py
bayesian_sgm/segmentator.py
bayesian_sgm-1.0.0.dist-info/LICENSE
bayesian_sgm-1.0.0.dist-info/METADATA
bayesian_sgm-1.0.0.dist-info/WHEEL
bayesian_sgm-1.0.0.dist-info/top_level.txt
bayesian_sgm-1.0.0.dist-info/RECORD
