Metadata-Version: 2.1
Name: bayesian-sgm
Version: 1.0.0
Summary: Um segmentador de cores bayesiano para a OpenCV.
Home-page: https://github.com/abnersn/bayesian_sgm
Author: Abner
Author-email: abnersousanascimento@gmail.com
License: UNKNOWN
Platform: UNKNOWN
Classifier: Programming Language :: Python :: 3.0
Classifier: License :: OSI Approved :: GNU General Public License v3 (GPLv3)
Classifier: Natural Language :: Portuguese (Brazilian)
Classifier: Topic :: Scientific/Engineering :: Image Recognition
Classifier: Topic :: Scientific/Engineering :: Artificial Intelligence
Classifier: Operating System :: OS Independent
Requires-Dist: opencv-python (>=3.1.0)
Requires-Dist: numpy (>=1.14.3)
